FBpyGIF/shuffle.py
FBpyGIF/args.py
FBpyGIF/fb.py
FBpyGIF/__main__.py
FBpyGIF/path.py
FBpyGIF/__init__.py
FBpyGIF/util.py
FBpyGIF/main.py
FBpyGIF-1.0.5.dist-info/RECORD
FBpyGIF-1.0.5.dist-info/DESCRIPTION.rst
FBpyGIF-1.0.5.dist-info/top_level.txt
FBpyGIF-1.0.5.dist-info/entry_points.txt
FBpyGIF-1.0.5.dist-info/metadata.json
FBpyGIF-1.0.5.dist-info/WHEEL
FBpyGIF-1.0.5.dist-info/METADATA
