Metadata-Version: 1.1
Name: FBpyGIF
Version: 1.0.5
Summary: Frame Buffer drawing libray with GIF support for Python3
Home-page: https://github.com/chidea/FBpyGIF
Author: Ch.Idea
Author-email: sbw228@gmail.com
License: MIT
Keywords: GIF animation raspberry pi rpi frame buffer fb
Platform: UNKNOWN
Classifier: Development Status :: 4 - Beta
Classifier: Intended Audience :: Developers
Classifier: Environment :: Console :: Framebuffer
Classifier: License :: OSI Approved :: MIT License
Classifier: Programming Language :: Python :: 3
Classifier: Programming Language :: Python :: 3.3
Classifier: Programming Language :: Python :: 3.4
Classifier: Programming Language :: Python :: 3.5
Classifier: Programming Language :: Python :: 3.6
Classifier: Natural Language :: English
